{
  "localhost": {
    "1100_Token_deploy.js": "1605450",
    "1200_NFT_deploy.js": "2186229",
    "1300_StakeDao_deploy.js": "1923209",
    "1400_StakeFlexible_deploy.js": "1695399",
    "1500_StakeLock_deploy.js": "2115591",
    "1600_DAO_deploy.js": "5171850",
    "1700_PrivateSale_deploy.js": "2000445",
    "1800_Airdrop_deploy.js": "1721168",
    "1900_Team_deploy.js": "1254879",
    "1202_NFT_createHolders.js": "16325772",
    "1502_StakeLock_1_maturity.js": "228478",
    "1503_StakeLock_3_maturity.js": "194316",
    "1504_StakeLock_6_maturity.js": "194304",
    "1505_StakeLock_12_maturity.js": "194340",
    "1602_DAO_Category_GameFi.js": "120037",
    "1603_DAO_Category_Metaverse.js": "122873",
    "1604_DAO_Category_Collaborations.js": "122933",
    "1605_DAO_Category_Investment.js": "122885",
    "1606_DAO_Category_Marketing.js": "122873",
    "1607_DAO_Category_Development.js": "122885",
    "1608_DAO_Category_Charities.js": "122849",
    "1609_DAO_Category_Advisors.js": "122849",
    "1610_DAO_Category_Treasury.js": "122861",
    "1611_DAO_Category_Bounties.js": "122801",
    "1612_DAO_Category_SocialFi.js": "122801",
    "2000_Token_setAddress.js": "46093",
    "2001_NFT_setAddresses.js": "46134",
    "2002_DAO_setAddress.js": "74226",
    "2003_DAO_setFirstDelegates.js": "209240",
    "3000_SendToken_StakeDao.js": "62916",
    "3001_SendToken_StakeFlexible.js": "62916",
    "3002_SendToken_StakeLock.js": "62916",
    "3003_SendToken_DAO.js": "62916",
    "3004_SendToken_PrivateSale.js": "62904",
    "3005_SendToken_Airdrop.js": "62904",
    "3006_SendToken_Team.js": "62916"
  },
  "cmle": {
    "1100_Token_deploy.js": "1551461",
    "1200_NFT_deploy.js": "2146790",
    "1202_NFT_createHolders.js": "16303870",
    "1300_StakeDao_deploy.js": "1923197",
    "1400_StakeFlexible_deploy.js": "1695387",
    "1500_StakeLock_deploy.js": "2115579",
    "1502_StakeLock_1_maturity.js": "228466",
    "1503_StakeLock_3_maturity.js": "194304",
    "1504_StakeLock_6_maturity.js": "194304",
    "1505_StakeLock_12_maturity.js": "194328",
    "1600_DAO_deploy.js": "5187604",
    "1602_DAO_Category_GameFi.js": "120069",
    "1603_DAO_Category_Metaverse.js": "122893",
    "1604_DAO_Category_Collaborations.js": "122953",
    "1605_DAO_Category_Investment.js": "122917",
    "1606_DAO_Category_Marketing.js": "122893",
    "1607_DAO_Category_Development.js": "122905",
    "1608_DAO_Category_Charities.js": "122869",
    "1609_DAO_Category_Advisors.js": "122869",
    "1610_DAO_Category_Treasury.js": "122881",
    "1611_DAO_Category_Bounties.js": "122845",
    "1612_DAO_Category_SocialFi.js": "122845",
    "1700_PrivateSale_deploy.js": "1933644",
    "1800_Airdrop_deploy.js": "1721168",
    "1900_Team_deploy.js": "1136771",
    "2000_Token_setAddress.js": "46093",
    "2001_NFT_setAddresses.js": "46178",
    "2002_DAO_setAddress.js": "74225",
    "2003_DAO_setFirstDelegates.js": "208398",
    "3000_SendToken_StakeDao.js": "59503",
    "3001_SendToken_StakeFlexible.js": "59503",
    "3002_SendToken_StakeLock.js": "59503",
    "3003_SendToken_DAO.js": "59491",
    "3004_SendToken_PrivateSale.js": "59491",
    "3005_SendToken_Airdrop.js": "59503",
    "3006_SendToken_Team.js": "59503"
  },
  "sepolia": {
    "1100_Token_deploy.js": "1580356",
    "1200_NFT_deploy.js": "2148830",
    "1202_NFT_createHolders.js": "16303894",
    "1300_StakeDao_deploy.js": "1923197",
    "1400_StakeFlexible_deploy.js": "1695387",
    "1500_StakeLock_deploy.js": "2115579",
    "1502_StakeLock_1_maturity.js": "228466",
    "1503_StakeLock_3_maturity.js": "194304",
    "1504_StakeLock_6_maturity.js": "194304",
    "1505_StakeLock_12_maturity.js": "194328",
    "1600_DAO_deploy.js": "5171814",
    "1800_Airdrop_deploy.js": "1721168",
    "2000_Token_setAddress.js": "46093",
    "2001_NFT_setAddresses.js": "29078",
    "2002_DAO_setAddress.js": "74238",
    "2003_DAO_setFirstDelegates.js": "209252",
    "1602_DAO_Category_GameFi.js": "120025",
    "1603_DAO_Category_Metaverse.js": "122849",
    "1604_DAO_Category_Collaborations.js": "122909",
    "1605_DAO_Category_Investment.js": "122873",
    "1606_DAO_Category_Marketing.js": "122849",
    "1607_DAO_Category_Development.js": "122861",
    "1608_DAO_Category_Charities.js": "122825",
    "1609_DAO_Category_Advisors.js": "122825",
    "1610_DAO_Category_Treasury.js": "122837",
    "1611_DAO_Category_Bounties.js": "122801",
    "1612_DAO_Category_SocialFi.js": "122801",
    "3000_SendToken_StakeDao.js": "62960",
    "3001_SendToken_StakeFlexible.js": "62960",
    "3002_SendToken_StakeLock.js": "62960",
    "3003_SendToken_DAO.js": "62960",
    "3005_SendToken_Airdrop.js": "62960",
    "1700_PrivateSale_deploy.js": "1933644",
    "3004_SendToken_PrivateSale.js": "59479",
    "1900_Team_deploy.js": "1136771",
    "3006_SendToken_Team.js": "62960"
  }
}